chephren/__init__.py
chephren/domain.py
chephren/website.py
chephren-0.1.0.dist-info/DESCRIPTION.rst
chephren-0.1.0.dist-info/METADATA
chephren-0.1.0.dist-info/metadata.json
chephren-0.1.0.dist-info/RECORD
chephren-0.1.0.dist-info/top_level.txt
chephren-0.1.0.dist-info/WHEEL
