Metadata-Version: 2.0
Name: chephren
Version: 0.1.0
Summary: An extension to Sphinx for managing a blog or static website
Home-page: UNKNOWN
Author: Vince Veselosky
Author-email: vince@veselosky.com
License: Apache 2.0
Platform: UNKNOWN
Classifier: Development Status :: 3 - Alpha
Classifier: License :: OSI Approved :: Apache Software License
Requires-Dist: werkzeug (>=0.10)
Requires-Dist: python-dateutil
Requires-Dist: pytz
Requires-Dist: sphinx (>=1.3.0)
